bookmd/__init__.py
bookmd/douban.py
bookmd/main.py
bookmd/metadata.py
bookmd/utils.py
bookmd-0.1.1.dist-info/DESCRIPTION.rst
bookmd-0.1.1.dist-info/METADATA
bookmd-0.1.1.dist-info/RECORD
bookmd-0.1.1.dist-info/WHEEL
bookmd-0.1.1.dist-info/entry_points.txt
bookmd-0.1.1.dist-info/metadata.json
bookmd-0.1.1.dist-info/top_level.txt
